signal_aspect_detection
