Metadata-Version: 2.1
Name: signal-aspect-detection
Version: 0.0.5
Summary: A railway signal aspect detection library
Home-page: https://gitlab.hpi.de/osm/drohnenflieger/signal-aspect-detection
Author: Dirk Friedenberger
Author-email: Dirk.Friedenberger@guest.hpi.de
License: MIT
Platform: UNKNOWN
